iDeployMaster/init.py
iDeployMaster/main.py
iDeployMaster-2.0.1.dist-info/METADATA
iDeployMaster-2.0.1.dist-info/WHEEL
iDeployMaster-2.0.1.dist-info/entry_points.txt
iDeployMaster-2.0.1.dist-info/top_level.txt
iDeployMaster-2.0.1.dist-info/RECORD
