Metadata-Version: 2.1
Name: iDeployMaster
Version: 2.0.1
Requires-Dist: Pillow
Requires-Dist: requests
